eques_elf/__init__.py
eques_elf/device.py
eques_elf/eques_local.py
eques_elf-0.0.2.dist-info/LICENSE
eques_elf-0.0.2.dist-info/METADATA
eques_elf-0.0.2.dist-info/WHEEL
eques_elf-0.0.2.dist-info/top_level.txt
eques_elf-0.0.2.dist-info/RECORD
