Metadata-Version: 2.1
Name: eques_elf
Version: 0.0.2
Summary: Eques Elf support for Python
Home-page: https://github.com/lgo/eques_elf
Author: Joey Pereira
Author-email: joey@pereira.io
License: UNKNOWN
Project-URL: Bug Tracker, https://github.com/lgo/eques_elf/issues
Keywords: eques elf,smart plug,iot,home assistant,hass
Platform: UNKNOWN
Classifier: Development Status :: 4 - Beta
Classifier: License :: OSI Approved :: MIT License
Classifier: Operating System :: OS Independent
Classifier: Programming Language :: Python :: 3
Classifier: Topic :: Software Development :: Libraries :: Python Modules
License-File: LICENSE
